{
	"function": "engineering",
	"cases": [
		{
			"description": "BIN2DEC positive binary",
			"setup": {},
			"formula": "BIN2DEC(\"1010\")",
			"expected": { "kind": "number", "value": 10 }
		},
		{
			"description": "BIN2DEC negative two's complement",
			"setup": {},
			"formula": "BIN2DEC(\"1111111111\")",
			"expected": { "kind": "number", "value": -1 }
		},
		{
			"description": "BIN2DEC invalid returns #NUM!",
			"setup": {},
			"formula": "BIN2DEC(\"102\")",
			"expected": { "kind": "error", "value": "#NUM!" }
		},
		{
			"description": "DEC2BIN positive",
			"setup": {},
			"formula": "DEC2BIN(10)",
			"expected": { "kind": "string", "value": "1010" }
		},
		{
			"description": "DEC2BIN with places",
			"setup": {},
			"formula": "DEC2BIN(5, 8)",
			"expected": { "kind": "string", "value": "00000101" }
		},
		{
			"description": "DEC2BIN out of range returns #NUM!",
			"setup": {},
			"formula": "DEC2BIN(600)",
			"expected": { "kind": "error", "value": "#NUM!" }
		},
		{
			"description": "HEX2DEC positive",
			"setup": {},
			"formula": "HEX2DEC(\"FF\")",
			"expected": { "kind": "number", "value": 255 }
		},
		{
			"description": "HEX2DEC negative",
			"setup": {},
			"formula": "HEX2DEC(\"FFFFFFFFFF\")",
			"expected": { "kind": "number", "value": -1 }
		},
		{
			"description": "DEC2HEX positive",
			"setup": {},
			"formula": "DEC2HEX(255)",
			"expected": { "kind": "string", "value": "FF" }
		},
		{
			"description": "DEC2HEX with places",
			"setup": {},
			"formula": "DEC2HEX(15, 4)",
			"expected": { "kind": "string", "value": "000F" }
		},
		{
			"description": "OCT2DEC positive",
			"setup": {},
			"formula": "OCT2DEC(\"77\")",
			"expected": { "kind": "number", "value": 63 }
		},
		{
			"description": "OCT2DEC invalid returns #NUM!",
			"setup": {},
			"formula": "OCT2DEC(\"89\")",
			"expected": { "kind": "error", "value": "#NUM!" }
		},
		{
			"description": "DEC2OCT positive",
			"setup": {},
			"formula": "DEC2OCT(63)",
			"expected": { "kind": "string", "value": "77" }
		},
		{
			"description": "DEC2OCT with places",
			"setup": {},
			"formula": "DEC2OCT(8, 4)",
			"expected": { "kind": "string", "value": "0010" }
		},
		{
			"description": "BIN2HEX via decimal",
			"setup": {},
			"formula": "BIN2HEX(\"1111\")",
			"expected": { "kind": "string", "value": "F" }
		},
		{
			"description": "BIN2OCT via decimal",
			"setup": {},
			"formula": "BIN2OCT(\"111\")",
			"expected": { "kind": "string", "value": "7" }
		},
		{
			"description": "HEX2BIN via decimal",
			"setup": {},
			"formula": "HEX2BIN(\"A\")",
			"expected": { "kind": "string", "value": "1010" }
		},
		{
			"description": "HEX2OCT via decimal",
			"setup": {},
			"formula": "HEX2OCT(\"F\")",
			"expected": { "kind": "string", "value": "17" }
		},
		{
			"description": "OCT2BIN via decimal",
			"setup": {},
			"formula": "OCT2BIN(\"7\")",
			"expected": { "kind": "string", "value": "111" }
		},
		{
			"description": "OCT2HEX via decimal",
			"setup": {},
			"formula": "OCT2HEX(\"17\")",
			"expected": { "kind": "string", "value": "F" }
		},
		{
			"description": "DELTA equal returns 1",
			"setup": {},
			"formula": "DELTA(5, 5)",
			"expected": { "kind": "number", "value": 1 }
		},
		{
			"description": "DELTA not equal returns 0",
			"setup": {},
			"formula": "DELTA(5, 3)",
			"expected": { "kind": "number", "value": 0 }
		},
		{
			"description": "DELTA default second arg 0",
			"setup": {},
			"formula": "DELTA(0)",
			"expected": { "kind": "number", "value": 1 }
		},
		{
			"description": "GESTEP num >= step returns 1",
			"setup": {},
			"formula": "GESTEP(5, 3)",
			"expected": { "kind": "number", "value": 1 }
		},
		{
			"description": "GESTEP num < step returns 0",
			"setup": {},
			"formula": "GESTEP(2, 5)",
			"expected": { "kind": "number", "value": 0 }
		},
		{
			"description": "GESTEP default step 0",
			"setup": {},
			"formula": "GESTEP(1)",
			"expected": { "kind": "number", "value": 1 }
		},
		{
			"description": "ERF.PRECISE one",
			"setup": {},
			"formula": "ERF.PRECISE(1)",
			"expected": { "kind": "number", "approx": 0.8427, "tolerance": 0.001 }
		},
		{
			"description": "ERFC zero",
			"setup": {},
			"formula": "ERFC(0)",
			"expected": { "kind": "number", "approx": 1, "tolerance": 0.00001 }
		},
		{
			"description": "ERFC.PRECISE one",
			"setup": {},
			"formula": "ERFC.PRECISE(1)",
			"expected": { "kind": "number", "approx": 0.1573, "tolerance": 0.001 }
		},
		{
			"description": "BESSELI fractional input order one",
			"setup": {},
			"formula": "BESSELI(1.5, 1)",
			"expected": { "kind": "number", "approx": 0.9816664289, "tolerance": 0.00001 }
		},
		{
			"description": "BESSELJ fractional input order one",
			"setup": {},
			"formula": "BESSELJ(1.5, 1)",
			"expected": { "kind": "number", "approx": 0.5579365079, "tolerance": 0.00001 }
		},
		{
			"description": "BESSELK fractional input order one",
			"setup": {},
			"formula": "BESSELK(2.5, 1)",
			"expected": { "kind": "number", "approx": 0.0738908163, "tolerance": 0.0001 }
		},
		{
			"description": "BESSELY fractional input order one",
			"setup": {},
			"formula": "BESSELY(2.5, 1)",
			"expected": { "kind": "number", "approx": 0.1459181379, "tolerance": 0.0001 }
		},
		{
			"description": "BITAND of 13 and 25",
			"setup": {},
			"formula": "BITAND(13,25)",
			"expected": { "kind": "number", "value": 9 }
		},
		{
			"description": "BITOR of 13 and 25",
			"setup": {},
			"formula": "BITOR(13,25)",
			"expected": { "kind": "number", "value": 29 }
		},
		{
			"description": "BITXOR of 13 and 25",
			"setup": {},
			"formula": "BITXOR(13,25)",
			"expected": { "kind": "number", "value": 20 }
		},
		{
			"description": "BITLSHIFT of 4 by 2",
			"setup": {},
			"formula": "BITLSHIFT(4,2)",
			"expected": { "kind": "number", "value": 16 }
		},
		{
			"description": "BITRSHIFT of 16 by 2",
			"setup": {},
			"formula": "BITRSHIFT(16,2)",
			"expected": { "kind": "number", "value": 4 }
		},
		{
			"description": "BITAND negative number returns #NUM!",
			"setup": {},
			"formula": "BITAND(-1,5)",
			"expected": { "kind": "error", "value": "#NUM!" }
		},
		{
			"description": "COMPLEX creates complex number string",
			"setup": {},
			"formula": "COMPLEX(3,4)",
			"expected": { "kind": "string", "value": "3+4i" }
		},
		{
			"description": "COMPLEX with j suffix",
			"setup": {},
			"formula": "COMPLEX(3,4,\"j\")",
			"expected": { "kind": "string", "value": "3+4j" }
		},
		{
			"description": "COMPLEX with zero imaginary",
			"setup": {},
			"formula": "COMPLEX(5,0)",
			"expected": { "kind": "string", "value": "5" }
		},
		{
			"description": "IMABS of 3+4i is 5",
			"setup": {},
			"formula": "IMABS(\"3+4i\")",
			"expected": { "kind": "number", "value": 5 }
		},
		{
			"description": "IMABS of real number",
			"setup": {},
			"formula": "IMABS(\"-5\")",
			"expected": { "kind": "number", "value": 5 }
		},
		{
			"description": "IMREAL extracts real part of complex number",
			"setup": {},
			"formula": "IMREAL(\"3+4i\")",
			"expected": { "kind": "number", "value": 3 }
		},
		{
			"description": "IMAGINARY extracts imaginary part of complex number",
			"setup": {},
			"formula": "IMAGINARY(\"3+4i\")",
			"expected": { "kind": "number", "value": 4 }
		},
		{
			"description": "IMCONJUGATE flips imaginary sign",
			"setup": {},
			"formula": "IMCONJUGATE(\"3+4i\")",
			"expected": { "kind": "string", "value": "3-4i" }
		},
		{
			"description": "IMSUM adds complex numbers",
			"setup": {},
			"formula": "IMSUM(\"3+4i\",\"1+2i\")",
			"expected": { "kind": "string", "value": "4+6i" }
		},
		{
			"description": "IMSUB subtracts complex numbers",
			"setup": {},
			"formula": "IMSUB(\"3+4i\",\"1+2i\")",
			"expected": { "kind": "string", "value": "2+2i" }
		},
		{
			"description": "IMPRODUCT multiplies complex numbers",
			"setup": {},
			"formula": "IMPRODUCT(\"1+2i\",\"3+4i\")",
			"expected": { "kind": "string", "value": "-5+10i" }
		},
		{
			"description": "IMDIV divides complex numbers",
			"setup": {},
			"formula": "IMDIV(\"-5+10i\",\"1+2i\")",
			"expected": { "kind": "string", "value": "3+4i" }
		},
		{
			"description": "IMSQRT of negative one",
			"setup": {},
			"formula": "IMSQRT(\"-1\")",
			"expected": { "kind": "string", "value": "i" }
		},
		{
			"description": "IMEXP zero",
			"setup": {},
			"formula": "IMEXP(\"0\")",
			"expected": { "kind": "string", "value": "1" }
		},
		{
			"description": "IMLN one",
			"setup": {},
			"formula": "IMLN(\"1\")",
			"expected": { "kind": "string", "value": "0" }
		},
		{
			"description": "IMLOG10 one hundred",
			"setup": {},
			"formula": "IMLOG10(\"100\")",
			"expected": { "kind": "string", "value": "2" }
		},
		{
			"description": "IMLOG2 eight",
			"setup": {},
			"formula": "IMLOG2(\"8\")",
			"expected": { "kind": "string", "value": "3" }
		},
		{
			"description": "IMSIN zero",
			"setup": {},
			"formula": "IMSIN(\"0\")",
			"expected": { "kind": "string", "value": "0" }
		},
		{
			"description": "IMCOS zero",
			"setup": {},
			"formula": "IMCOS(\"0\")",
			"expected": { "kind": "string", "value": "1" }
		},
		{
			"description": "IMARGUMENT of 1+i returns pi/4",
			"setup": {},
			"formula": "IMARGUMENT(\"1+i\")",
			"expected": { "kind": "number", "approx": 0.7853981633974483, "tolerance": 1e-8 }
		},
		{
			"description": "IMARGUMENT of 0 returns #DIV/0!",
			"setup": {},
			"formula": "IMARGUMENT(\"0\")",
			"expected": { "kind": "error", "value": "#DIV/0!" }
		},
		{
			"description": "IMPOWER squares a complex number",
			"setup": {},
			"formula": "IMPOWER(\"1+1i\",2)",
			"expected": { "kind": "string", "value": "2i" }
		}
	]
}
